kukiapipy/__init__.py
kukiapipy/kuki.py
kukiapipy-0.6.dist-info/LICENSE
kukiapipy-0.6.dist-info/METADATA
kukiapipy-0.6.dist-info/WHEEL
kukiapipy-0.6.dist-info/top_level.txt
kukiapipy-0.6.dist-info/RECORD
